{
    "total": [
        {
            "id": "100010759066019",
            "count": 0
        },
        {
            "id": "100057597799449",
            "count": 0
        },
        {
            "id": "100073196289058",
            "count": 0
        },
        {
            "id": "100053915443051",
            "count": 0
        },
        {
            "id": "100028635525762",
            "count": 0
        },
        {
            "id": "100076671286206",
            "count": 0
        },
        {
            "id": "100076242982116",
            "count": 0
        },
        {
            "id": "100038625191514",
            "count": 0
        },
        {
            "id": "100053848133650",
            "count": 0
        },
        {
            "id": "100019817876791",
            "count": 0
        },
        {
            "id": "100058421533142",
            "count": 0
        },
        {
            "id": "100074265693328",
            "count": 0
        },
        {
            "id": "100084794796348",
            "count": 1
        },
        {
            "id": "100028881279853",
            "count": 0
        },
        {
            "id": "100069668822813",
            "count": 0
        },
        {
            "id": "100078274027212",
            "count": 0
        },
        {
            "id": "100089888905746",
            "count": 0
        },
        {
            "id": "100054122115769",
            "count": 0
        },
        {
            "id": "100004386911953",
            "count": 1
        },
        {
            "id": "100063152354940",
            "count": 1
        },
        {
            "id": "100033825674259",
            "count": 0
        },
        {
            "id": "100083967159361",
            "count": 0
        },
        {
            "id": "100071479728677",
            "count": 0
        },
        {
            "id": "100014339913457",
            "count": 0
        },
        {
            "id": "61554482439731",
            "count": 0
        },
        {
            "id": "100079547949464",
            "count": 0
        },
        {
            "id": "100035051168944",
            "count": 1
        },
        {
            "id": "100018314948779",
            "count": 0
        },
        {
            "id": "100075606393499",
            "count": 0
        },
        {
            "id": "100069364601000",
            "count": 0
        },
        {
            "id": "100060894693968",
            "count": 3
        },
        {
            "id": "100051801832642",
            "count": 0
        },
        {
            "id": "100039501849411",
            "count": 0
        },
        {
            "id": "100011454722612",
            "count": 0
        },
        {
            "id": "100075122010077",
            "count": 0
        },
        {
            "id": "100081089322687",
            "count": 0
        },
        {
            "id": "61558524225388",
            "count": 0
        },
        {
            "id": "100075863781789",
            "count": 66
        },
        {
            "id": "100043630283156",
            "count": 0
        },
        {
            "id": "100058466021567",
            "count": 0
        }
    ],
    "week": [
        {
            "id": "100010759066019",
            "count": 0
        },
        {
            "id": "100057597799449",
            "count": 0
        },
        {
            "id": "100073196289058",
            "count": 0
        },
        {
            "id": "100053915443051",
            "count": 0
        },
        {
            "id": "100028635525762",
            "count": 0
        },
        {
            "id": "100076671286206",
            "count": 0
        },
        {
            "id": "100076242982116",
            "count": 0
        },
        {
            "id": "100038625191514",
            "count": 0
        },
        {
            "id": "100053848133650",
            "count": 0
        },
        {
            "id": "100019817876791",
            "count": 0
        },
        {
            "id": "100058421533142",
            "count": 0
        },
        {
            "id": "100074265693328",
            "count": 0
        },
        {
            "id": "100084794796348",
            "count": 1
        },
        {
            "id": "100028881279853",
            "count": 0
        },
        {
            "id": "100069668822813",
            "count": 0
        },
        {
            "id": "100078274027212",
            "count": 0
        },
        {
            "id": "100089888905746",
            "count": 0
        },
        {
            "id": "100054122115769",
            "count": 0
        },
        {
            "id": "100004386911953",
            "count": 1
        },
        {
            "id": "100063152354940",
            "count": 1
        },
        {
            "id": "100033825674259",
            "count": 0
        },
        {
            "id": "100083967159361",
            "count": 0
        },
        {
            "id": "100071479728677",
            "count": 0
        },
        {
            "id": "100014339913457",
            "count": 0
        },
        {
            "id": "61554482439731",
            "count": 0
        },
        {
            "id": "100079547949464",
            "count": 0
        },
        {
            "id": "100035051168944",
            "count": 1
        },
        {
            "id": "100018314948779",
            "count": 0
        },
        {
            "id": "100075606393499",
            "count": 0
        },
        {
            "id": "100069364601000",
            "count": 0
        },
        {
            "id": "100060894693968",
            "count": 3
        },
        {
            "id": "100051801832642",
            "count": 0
        },
        {
            "id": "100039501849411",
            "count": 0
        },
        {
            "id": "100011454722612",
            "count": 0
        },
        {
            "id": "100075122010077",
            "count": 0
        },
        {
            "id": "100081089322687",
            "count": 0
        },
        {
            "id": "61558524225388",
            "count": 0
        },
        {
            "id": "100075863781789",
            "count": 66
        },
        {
            "id": "100043630283156",
            "count": 0
        },
        {
            "id": "100058466021567",
            "count": 0
        }
    ],
    "day": [
        {
            "id": "100010759066019",
            "count": 0,
            "name": "Đậu Đậu"
        },
        {
            "id": "100057597799449",
            "count": 0,
            "name": "Tạ Ngọc Ánh"
        },
        {
            "id": "100073196289058",
            "count": 0,
            "name": "Nguyễn Huy"
        },
        {
            "id": "100053915443051",
            "count": 0,
            "name": "Chử Văn Minh"
        },
        {
            "id": "100028635525762",
            "count": 0,
            "name": "Minh"
        },
        {
            "id": "100076671286206",
            "count": 0,
            "name": "Lynh Dayy"
        },
        {
            "id": "100076242982116",
            "count": 0,
            "name": "Bé Ánhh"
        },
        {
            "id": "100038625191514",
            "count": 0,
            "name": "Mai Thị Ngọc Khánh"
        },
        {
            "id": "100053848133650",
            "count": 0,
            "name": "Trung Nguyễn"
        },
        {
            "id": "100019817876791",
            "count": 0,
            "name": "Dt Ngocc Maii"
        },
        {
            "id": "100058421533142",
            "count": 0,
            "name": "Nguyễn Ngọc Thiên Dũng"
        },
        {
            "id": "100074265693328",
            "count": 0,
            "name": "Người dùng facebook"
        },
        {
            "id": "100084794796348",
            "count": 0,
            "name": "Đào Ngọc Nguyên"
        },
        {
            "id": "100028881279853",
            "count": 0,
            "name": "Nguyễn Huy"
        },
        {
            "id": "100069668822813",
            "count": 0,
            "name": "Nguyễn Hưng"
        },
        {
            "id": "100078274027212",
            "count": 0,
            "name": "Hoàng Hải"
        },
        {
            "id": "100089888905746",
            "count": 0,
            "name": "Người dùng facebook"
        },
        {
            "id": "100054122115769",
            "count": 0,
            "name": "Người dùng facebook"
        },
        {
            "id": "100004386911953",
            "count": 0,
            "name": "Hồ Đắc Tuấn"
        },
        {
            "id": "100063152354940",
            "count": 0,
            "name": "Dương Vĩ"
        },
        {
            "id": "100033825674259",
            "count": 0,
            "name": "Phạm Trung"
        },
        {
            "id": "100083967159361",
            "count": 0,
            "name": "Nguyễn Trọng Phụng"
        },
        {
            "id": "100071479728677",
            "count": 0,
            "name": "Nhật Minh"
        },
        {
            "id": "100014339913457",
            "count": 0,
            "name": "Pham Van Hieu"
        },
        {
            "id": "61554482439731",
            "count": 0,
            "name": "Huyền Linh"
        },
        {
            "id": "100079547949464",
            "count": 0,
            "name": "Xuân Tiến"
        },
        {
            "id": "100035051168944",
            "count": 0,
            "name": "Ngọc Ánh"
        },
        {
            "id": "100018314948779",
            "count": 0,
            "name": "Minh Trang"
        },
        {
            "id": "100075606393499",
            "count": 0,
            "name": "Minh Khải"
        },
        {
            "id": "100069364601000",
            "count": 0,
            "name": "Phạm Vân"
        },
        {
            "id": "100060894693968",
            "count": 0,
            "name": "Lê Minh Tiến"
        },
        {
            "id": "100051801832642",
            "count": 0,
            "name": "Harry Maguire"
        },
        {
            "id": "100039501849411",
            "count": 0,
            "name": "Vũ Thành An"
        },
        {
            "id": "100011454722612",
            "count": 0,
            "name": "Hoàng Tú"
        },
        {
            "id": "100075122010077",
            "count": 0,
            "name": "Quang Huy"
        },
        {
            "id": "100081089322687",
            "count": 0,
            "name": "Khoa Lê"
        },
        {
            "id": "61558524225388",
            "count": 0,
            "name": "Su Ri"
        },
        {
            "id": "100075863781789",
            "count": 5,
            "name": "Ngọc Nguyên"
        },
        {
            "id": "100043630283156",
            "count": 0,
            "name": "Hoa Cà"
        },
        {
            "id": "100058466021567",
            "count": 0,
            "name": "T. Trực"
        }
    ],
    "time": 2,
    "last": {
        "time": 0,
        "day": [
            {
                "id": "100010759066019",
                "count": 0,
                "name": "Đậu Đậu"
            },
            {
                "id": "100057597799449",
                "count": 0,
                "name": "Tạ Ngọc Ánh"
            },
            {
                "id": "100073196289058",
                "count": 0,
                "name": "Nguyễn Huy"
            },
            {
                "id": "100053915443051",
                "count": 0,
                "name": "Chử Văn Minh"
            },
            {
                "id": "100028635525762",
                "count": 0,
                "name": "Minh"
            },
            {
                "id": "100076671286206",
                "count": 0,
                "name": "Lynh Dayy"
            },
            {
                "id": "100076242982116",
                "count": 0,
                "name": "Bé Ánhh"
            },
            {
                "id": "100038625191514",
                "count": 0,
                "name": "Mai Thị Ngọc Khánh"
            },
            {
                "id": "100053848133650",
                "count": 0,
                "name": "Trung Nguyễn"
            },
            {
                "id": "100019817876791",
                "count": 0,
                "name": "Dt Ngocc Maii"
            },
            {
                "id": "100058421533142",
                "count": 0,
                "name": "Nguyễn Ngọc Thiên Dũng"
            },
            {
                "id": "100074265693328",
                "count": 0,
                "name": "Người dùng facebook"
            },
            {
                "id": "100084794796348",
                "count": 0,
                "name": "Đào Ngọc Nguyên"
            },
            {
                "id": "100028881279853",
                "count": 0,
                "name": "Nguyễn Huy"
            },
            {
                "id": "100069668822813",
                "count": 0,
                "name": "Nguyễn Hưng"
            },
            {
                "id": "100078274027212",
                "count": 0,
                "name": "Hoàng Hải"
            },
            {
                "id": "100089888905746",
                "count": 0,
                "name": "Người dùng facebook"
            },
            {
                "id": "100054122115769",
                "count": 0,
                "name": "Người dùng facebook"
            },
            {
                "id": "100004386911953",
                "count": 0,
                "name": "Hồ Đắc Tuấn"
            },
            {
                "id": "100063152354940",
                "count": 0,
                "name": "Dương Vĩ"
            },
            {
                "id": "100033825674259",
                "count": 0,
                "name": "Phạm Trung"
            },
            {
                "id": "100083967159361",
                "count": 0,
                "name": "Nguyễn Trọng Phụng"
            },
            {
                "id": "100071479728677",
                "count": 0,
                "name": "Nhật Minh"
            },
            {
                "id": "100014339913457",
                "count": 0,
                "name": "Pham Van Hieu"
            },
            {
                "id": "61554482439731",
                "count": 0,
                "name": "Huyền Linh"
            },
            {
                "id": "100079547949464",
                "count": 0,
                "name": "Xuân Tiến"
            },
            {
                "id": "100035051168944",
                "count": 0,
                "name": "Ngọc Ánh"
            },
            {
                "id": "100018314948779",
                "count": 0,
                "name": "Minh Trang"
            },
            {
                "id": "100075606393499",
                "count": 0,
                "name": "Minh Khải"
            },
            {
                "id": "100069364601000",
                "count": 0,
                "name": "Phạm Vân"
            },
            {
                "id": "100060894693968",
                "count": 0,
                "name": "Lê Minh Tiến"
            },
            {
                "id": "100051801832642",
                "count": 0,
                "name": "Harry Maguire"
            },
            {
                "id": "100039501849411",
                "count": 0,
                "name": "Vũ Thành An"
            },
            {
                "id": "100011454722612",
                "count": 0,
                "name": "Hoàng Tú"
            },
            {
                "id": "100075122010077",
                "count": 0,
                "name": "Quang Huy"
            },
            {
                "id": "100081089322687",
                "count": 0,
                "name": "Khoa Lê"
            },
            {
                "id": "61558524225388",
                "count": 0,
                "name": "Su Ri"
            },
            {
                "id": "100075863781789",
                "count": 3,
                "name": "Ngọc Nguyên"
            },
            {
                "id": "100043630283156",
                "count": 0,
                "name": "Hoa Cà"
            },
            {
                "id": "100058466021567",
                "count": 0,
                "name": "T. Trực"
            }
        ],
        "week": [
            {
                "id": "100010759066019",
                "count": 0
            },
            {
                "id": "100057597799449",
                "count": 0
            },
            {
                "id": "100073196289058",
                "count": 0
            },
            {
                "id": "100053915443051",
                "count": 0
            },
            {
                "id": "100028635525762",
                "count": 0
            },
            {
                "id": "100076671286206",
                "count": 0
            },
            {
                "id": "100076242982116",
                "count": 0
            },
            {
                "id": "100038625191514",
                "count": 0
            },
            {
                "id": "100053848133650",
                "count": 0
            },
            {
                "id": "100019817876791",
                "count": 0
            },
            {
                "id": "100058421533142",
                "count": 0
            },
            {
                "id": "100074265693328",
                "count": 0
            },
            {
                "id": "100084794796348",
                "count": 0
            },
            {
                "id": "100028881279853",
                "count": 0
            },
            {
                "id": "100069668822813",
                "count": 0
            },
            {
                "id": "100078274027212",
                "count": 0
            },
            {
                "id": "100089888905746",
                "count": 0
            },
            {
                "id": "100054122115769",
                "count": 0
            },
            {
                "id": "100004386911953",
                "count": 0
            },
            {
                "id": "100063152354940",
                "count": 0
            },
            {
                "id": "100033825674259",
                "count": 0
            },
            {
                "id": "100083967159361",
                "count": 0
            },
            {
                "id": "100071479728677",
                "count": 0
            },
            {
                "id": "100014339913457",
                "count": 0
            },
            {
                "id": "61554482439731",
                "count": 0
            },
            {
                "id": "100079547949464",
                "count": 0
            },
            {
                "id": "100035051168944",
                "count": 0
            },
            {
                "id": "100018314948779",
                "count": 0
            },
            {
                "id": "100075606393499",
                "count": 0
            },
            {
                "id": "100069364601000",
                "count": 0
            },
            {
                "id": "100060894693968",
                "count": 0
            },
            {
                "id": "100051801832642",
                "count": 0
            },
            {
                "id": "100039501849411",
                "count": 0
            },
            {
                "id": "100011454722612",
                "count": 0
            },
            {
                "id": "100075122010077",
                "count": 0
            },
            {
                "id": "100081089322687",
                "count": 0
            },
            {
                "id": "61558524225388",
                "count": 0
            },
            {
                "id": "100075863781789",
                "count": 0
            },
            {
                "id": "100043630283156",
                "count": 0
            },
            {
                "id": "100058466021567",
                "count": 0
            }
        ]
    }
}